{"provides":{"Dist::Metadata::Dir":{"version":"0.923","file":"Dist/Metadata/Dir.pm"},"Dist::Metadata::Zip":{"version":"0.923","file":"Dist/Metadata/Zip.pm"},"Dist::Metadata":{"version":"0.923","file":"Dist/Metadata.pm"},"Dist::Metadata::Tar":{"version":"0.923","file":"Dist/Metadata/Tar.pm"},"Dist::Metadata::Struct":{"version":"0.923","file":"Dist/Metadata/Struct.pm"},"Dist::Metadata::Archive":{"version":"0.923","file":"Dist/Metadata/Archive.pm"},"Dist::Metadata::Dist":{"version":"0.923","file":"Dist/Metadata/Dist.pm"}},"target":"Dist::Metadata","version":"0.923","name":"Dist::Metadata","dist":"Dist-Metadata-0.923","pathname":"R/RW/RWSTAUNER/Dist-Metadata-0.923.tar.gz"}