{"provides":{"DBIx::Inspector":{"version":"0.06","file":"DBIx/Inspector.pm"},"DBIx::Inspector::Driver::Base":{"file":"DBIx/Inspector/Driver/Base.pm"},"DBIx::Inspector::Column::Pg":{"file":"DBIx/Inspector/Column/Pg.pm"},"DBIx::Inspector::Table":{"file":"DBIx/Inspector/Table.pm"},"DBIx::Inspector::Iterator":{"file":"DBIx/Inspector/Iterator.pm"},"DBIx::Inspector::ForeignKey::Pg":{"file":"DBIx/Inspector/ForeignKey/Pg.pm"},"DBIx::Inspector::Driver::Pg":{"file":"DBIx/Inspector/Driver/Pg.pm"},"DBIx::Inspector::ForeignKey":{"file":"DBIx/Inspector/ForeignKey.pm"},"DBIx::Inspector::Column":{"file":"DBIx/Inspector/Column.pm"},"DBIx::Inspector::Table::Pg":{"file":"DBIx/Inspector/Table/Pg.pm"},"DBIx::Inspector::Iterator::Null":{"file":"DBIx/Inspector/Iterator/Null.pm"},"DBIx::Inspector::Driver::SQLite":{"file":"DBIx/Inspector/Driver/SQLite.pm"},"DBIx::Inspector::Driver::mysql":{"file":"DBIx/Inspector/Driver/mysql.pm"}},"target":"DBIx::Inspector","version":"0.06","name":"DBIx::Inspector","dist":"DBIx-Inspector-0.06","pathname":"T/TO/TOKUHIROM/DBIx-Inspector-0.06.tar.gz"}